LICENSE
README.md
setup.py
ghostpip/__init__.py
ghostpip/balance.py
ghostpip/birth.py
ghostpip/device.py
ghostpip/getuser.py
ghostpip/location.py
ghostpip/nid.py
ghostpip/signin.py
ghostpip/signup.py
ghostpip/sim.py
ghostpip/simitalk.py
ghostpip/simiteach.py
ghostpip.egg-info/PKG-INFO
ghostpip.egg-info/SOURCES.txt
ghostpip.egg-info/dependency_links.txt
ghostpip.egg-info/requires.txt
ghostpip.egg-info/top_level.txt