Metadata-Version: 2.1
Name: ghostpip
Version: 1.1.1
Summary: A Python module for interacting with the ghost.toxinum.xyz API
Home-page: https://github.com/illusionghost3/ghostpip
Author: Mohammad Alamin
Author-email: akxvau@gmail.com
License: MIT
Keywords: ghostpip api module
Classifier: Development Status :: 5 - Production/Stable
Classifier: Intended Audience :: Developers
Classifier: License :: OSI Approved :: MIT License
Classifier: Programming Language :: Python :: 3
Classifier: Programming Language :: Python :: 3.6
Classifier: Programming Language :: Python :: 3.7
Classifier: Programming Language :: Python :: 3.8
Classifier: Programming Language :: Python :: 3.9
Classifier: Programming Language :: Python :: 3.10
Classifier: Programming Language :: Python :: 3.11
License-File: LICENSE
